{
  "name": "El_Ice",
  "untill": 0,
  "grid": [
    1,
    1
  ],
  "axis": [
    59,
    59
  ],
  "marginx": 0,
  "marginy": 0,
  "imgWidth": 115,
  "imgHeight": 115,
  "width": 119,
  "height": 119,
  "offx": 0,
  "offy": 0,
  "origname": "i3259afb1-de41-465a-be2f-79733e0f03da.png",
  "source": "/home/alexis/git/NOThInG/Img/ice.png",
  "shape": "rect",
  "left": 59,
  "right": 60,
  "top": 59,
  "bottom": 60,
  "uid": "3259afb1-de41-465a-be2f-79733e0f03da",
  "lastmod": 1570322713056,
  "r": 59,
  "tiled": true
}
