{
  "name": "wall_top_right",
  "untill": 0,
  "grid": [
    1,
    1
  ],
  "axis": [
    59,
    59
  ],
  "marginx": 0,
  "marginy": 0,
  "imgWidth": 119,
  "imgHeight": 119,
  "width": 119,
  "height": 119,
  "offx": 0,
  "offy": 0,
  "origname": "i763e2672-730c-431c-9031-abb81d6e8e31.png",
  "source": "C:\\Users\\Orion\\Documents\\Projets\\NOThInG\\Img\\wall_top_right.png",
  "shape": "rect",
  "left": 59,
  "right": 60,
  "top": 59,
  "bottom": 60,
  "uid": "763e2672-730c-431c-9031-abb81d6e8e31"
}
